WerkzeugSecurityCLI/__init__.py
WerkzeugSecurityCLI-1.1.0.dist-info/LICENSE
WerkzeugSecurityCLI-1.1.0.dist-info/METADATA
WerkzeugSecurityCLI-1.1.0.dist-info/WHEEL
WerkzeugSecurityCLI-1.1.0.dist-info/entry_points.txt
WerkzeugSecurityCLI-1.1.0.dist-info/top_level.txt
WerkzeugSecurityCLI-1.1.0.dist-info/RECORD
