Metadata-Version: 2.1
Name: WerkzeugSecurityCLI
Version: 1.1.0
Summary: Generate and check werkzeug.security password hashes on the command line
License:                     GNU GENERAL PUBLIC LICENSE
Project-URL: Homepage, https://github.com/jb2170/WerkzeugSecurityCLI/
License-File: LICENSE
Requires-Dist: Werkzeug
